based_user/__init__.py
based_user/admin.py
based_user/apps.py
based_user/models.py
django_based_user-0.1.3.dist-info/LICENSE
django_based_user-0.1.3.dist-info/METADATA
django_based_user-0.1.3.dist-info/WHEEL
django_based_user-0.1.3.dist-info/RECORD
