Metadata-Version: 2.1
Name: django-based-user
Version: 0.1.3
Summary: A more based base user model for Django.
Home-page: https://github.com/hoganld/django-based-user/
License: MIT
Author: Luke Hogan
Requires-Python: >=3.9
Classifier: Development Status :: 4 - Beta
Classifier: Framework :: Django :: 4.2
Classifier: Framework :: Django :: 5.0
Classifier: License :: OSI Approved :: MIT License
Classifier: Programming Language :: Python :: 3
Classifier: Programming Language :: Python :: 3.9
Classifier: Programming Language :: Python :: 3.10
Classifier: Programming Language :: Python :: 3.11
Classifier: Programming Language :: Python :: 3.12
Requires-Dist: django (>=4.2)
Project-URL: Repository, https://github.com/hoganld/django-based-user/
